viashpy/__init__.py
viashpy/__version__.py
viashpy/_run.py
viashpy/config.py
viashpy/testing.py
viashpy/types.py
viashpy/utils.py
viashpy-0.9.0.dist-info/LICENSE
viashpy-0.9.0.dist-info/METADATA
viashpy-0.9.0.dist-info/WHEEL
viashpy-0.9.0.dist-info/entry_points.txt
viashpy-0.9.0.dist-info/top_level.txt
viashpy-0.9.0.dist-info/RECORD
