Metadata-Version: 2.1
Name: viashpy
Version: 0.9.0
Summary: A plugin with various tools and utilities to interact with viash using python.
Author: Dries Schaumont
Author-email: dries@data-intuitive.com
Maintainer: Dries Schaumont
Maintainer-email: dries@data-intuitive.com
License: MIT
Classifier: Development Status :: 4 - Beta
Classifier: Framework :: Pytest
Classifier: Intended Audience :: Developers
Classifier: Topic :: Software Development :: Testing
Classifier: Programming Language :: Python
Classifier: Programming Language :: Python :: 3
Classifier: Programming Language :: Python :: 3.9
Classifier: Programming Language :: Python :: 3.10
Classifier: Programming Language :: Python :: 3.11
Classifier: Programming Language :: Python :: 3.12
Classifier: Programming Language :: Python :: 3.13
Classifier: Programming Language :: Python :: 3 :: Only
Classifier: Operating System :: OS Independent
Classifier: License :: OSI Approved :: GNU General Public License v3 (GPLv3)
Requires-Python: >=3.8
License-File: LICENSE
Requires-Dist: pytest>=6.2
Requires-Dist: PyYAML~=6.0
Provides-Extra: dev
Requires-Dist: tox; extra == "dev"
